README
setup.py
geokit/__init__.py
geokit/geocoders.py
geokit.egg-info/PKG-INFO
geokit.egg-info/SOURCES.txt
geokit.egg-info/dependency_links.txt
geokit.egg-info/requires.txt
geokit.egg-info/top_level.txt