Metadata-Version: 1.0
Name: geokit
Version: 0.0.3
Summary: Geocoding toolkit
Home-page: UNKNOWN
Author: Alex Toney
Author-email: toneyalex@gmail.com
License: BSD
Platform: any
